[
  {
    "name": "LEATHER COAT WITH PATCH STUDIO NICHOLSON",
    "price": 249000,
    "discount": 90,
    "link": "https://www.zara.com/in/en/leather-coat-with-patch-studio-nicholson-p02521502.html?v1=187003814"
  },
  {
    "name": "PEA COAT WITH LEATHER PATCHES STUDIO NICHOLSON",
    "price": 249000,
    "discount": 88,
    "link": "https://www.zara.com/in/en/pea-coat-with-leather-patches-studio-nicholson-p02521501.html?v1=187003815"
  },
  {
    "name": "WATER-REPELLENT TRENCH COAT",
    "price": 249000,
    "discount": 85,
    "link": "https://www.zara.com/in/en/water-repellent-trench-coat-p00706385.html?v1=195880545"
  },
  {
    "name": "WATER-REPELLENT TRENCH COAT STUDIO NICHOLSON",
    "price": 249000,
    "discount": 82,
    "link": "https://www.zara.com/in/en/water-repellent-trench-coat-studio-nicholson-p06518500.html?v1=184764082"
  },
  {
    "name": "COAT - DOWN GILET",
    "price": 249000,
    "discount": 82,
    "link": "https://www.zara.com/in/en/coat---down-gilet-p09621313.html?v1=191588760"
  },
  {
    "name": "WOOL BLEND COAT",
    "price": 249000,
    "discount": 82,
    "link": "https://www.zara.com/in/en/wool-blend-coat-p05992123.html?v1=207850008"
  },
  {
    "name": "FAUX LEATHER BERMUDA SHORTS",
    "price": 59000,
    "discount": 80,
    "link": "https://www.zara.com/in/en/faux-leather-bermuda-shorts-p05070461.html?v1=186006602"
  },
  {
    "name": "OVERSIZE HOODIE STUDIO NICHOLSON",
    "price": 129000,
    "discount": 78,
    "link": "https://www.zara.com/in/en/oversize-hoodie-studio-nicholson-p05372385.html?v1=198063940"
  },
  {
    "name": "100% WOOL BLAZER",
    "price": 249000,
    "discount": 77,
    "link": "https://www.zara.com/in/en/100-wool-blazer-p05931543.html?v1=197317096"
  },
  {
    "name": "COTTON TRENCH COAT",
    "price": 249000,
    "discount": 77,
    "link": "https://www.zara.com/in/en/cotton-trench-coat-p00706370.html?v1=203017381"
  },
  {
    "name": "PADDED TEXTURED COAT",
    "price": 249000,
    "discount": 75,
    "link": "https://www.zara.com/in/en/padded-textured-coat-p03046474.html?v1=197519680"
  },
  {
    "name": "WOOL BLEND COAT",
    "price": 249000,
    "discount": 75,
    "link": "https://www.zara.com/in/en/wool-blend-coat-p03046472.html?v1=195655451"
  },
  {
    "name": "DOUBLE-BREASTED SUIT BLAZER",
    "price": 249000,
    "discount": 75,
    "link": "https://www.zara.com/in/en/double-breasted-suit-blazer-p00340315.html?v1=192126166"
  },
  {
    "name": "SHIMMERY DOUBLE-BREASTED BLAZER",
    "price": 249000,
    "discount": 75,
    "link": "https://www.zara.com/in/en/shimmery-double-breasted-blazer-p09621650.html?v1=193149847"
  },
  {
    "name": "LINEN BLEND BLAZER",
    "price": 249000,
    "discount": 75,
    "link": "https://www.zara.com/in/en/linen-blend-blazer-p00706356.html?v1=186026977"
  },
  {
    "name": "TECHNICAL PARKA",
    "price": 249000,
    "discount": 75,
    "link": "https://www.zara.com/in/en/technical-parka-p07380641.html?v1=184857820"
  },
  {
    "name": "WIDE FIT TROUSERS",
    "price": 129000,
    "discount": 74,
    "link": "https://www.zara.com/in/en/wide-fit-trousers-p02553322.html?v1=188530165"
  },
  {
    "name": "CHINO TROUSERS",
    "price": 129000,
    "discount": 74,
    "link": "https://www.zara.com/in/en/chino-trousers-p06861362.html?v1=203015442"
  },
  {
    "name": "STRAIGHT FIT SUIT TROUSERS",
    "price": 129000,
    "discount": 74,
    "link": "https://www.zara.com/in/en/straight-fit-suit-trousers-p00340316.html?v1=192126164"
  },
  {
    "name": "CORDUROY OVERSHIRT",
    "price": 129000,
    "discount": 74,
    "link": "https://www.zara.com/in/en/corduroy-overshirt-p01538317.html?v1=192067834"
  },
  {
    "name": "PLEATED SATIN TROUSERS",
    "price": 129000,
    "discount": 74,
    "link": "https://www.zara.com/in/en/pleated-satin-trousers-p09621653.html?v1=193162627"
  },
  {
    "name": "PLEATED SATIN TROUSERS",
    "price": 129000,
    "discount": 74,
    "link": "https://www.zara.com/in/en/pleated-satin-trousers-p09621653.html?v1=193162628"
  },
  {
    "name": "WIDE FIT TROUSERS",
    "price": 129000,
    "discount": 74,
    "link": "https://www.zara.com/in/en/wide-fit-trousers-p08288850.html?v1=183703967"
  },
  {
    "name": "SUIT JOGGER WAIST TROUSERS",
    "price": 129000,
    "discount": 74,
    "link": "https://www.zara.com/in/en/suit-jogger-waist-trousers-p02674305.html?v1=191113319"
  },
  {
    "name": "STRIPED TEXTURED SHIRT",
    "price": 79000,
    "discount": 73,
    "link": "https://www.zara.com/in/en/striped-textured-shirt-p03057170.html?v1=185138279"
  },
  {
    "name": "TRAINING TANK TOP",
    "price": 79000,
    "discount": 73,
    "link": "https://www.zara.com/in/en/training-tank-top-p00347465.html?v1=206289490"
  },
  {
    "name": "TRAINING TANK TOP",
    "price": 79000,
    "discount": 73,
    "link": "https://www.zara.com/in/en/training-tank-top-p00347465.html?v1=206289489"
  },
  {
    "name": "SUIT BLAZER",
    "price": 249000,
    "discount": 72,
    "link": "https://www.zara.com/in/en/suit-blazer-p05808494.html?v1=188812541"
  },
  {
    "name": "RELAXED FIT TRENCH COAT",
    "price": 249000,
    "discount": 72,
    "link": "https://www.zara.com/in/en/relaxed-fit-trench-coat-p00706333.html?v1=201660857"
  },
  {
    "name": "SUIT BLAZER",
    "price": 249000,
    "discount": 72,
    "link": "https://www.zara.com/in/en/suit-blazer-p05851281.html?v1=190501487"
  },
  {
    "name": "TEXTURED SUIT BLAZER",
    "price": 249000,
    "discount": 72,
    "link": "https://www.zara.com/in/en/textured-suit-blazer-p00706334.html?v1=182871841"
  },
  {
    "name": "SUIT BLAZER",
    "price": 249000,
    "discount": 72,
    "link": "https://www.zara.com/in/en/suit-blazer-p02674310.html?v1=191584773"
  },
  {
    "name": "COTTON PARKA",
    "price": 249000,
    "discount": 72,
    "link": "https://www.zara.com/in/en/cotton-parka-p00706327.html?v1=187709936"
  },
  {
    "name": "WATER-REPELLENT TECHNICAL JACKET",
    "price": 199000,
    "discount": 71,
    "link": "https://www.zara.com/in/en/water-repellent-technical-jacket-p03918101.html?v1=200060702"
  },
  {
    "name": "TEXTURED JACKET",
    "price": 199000,
    "discount": 71,
    "link": "https://www.zara.com/in/en/textured-jacket-p00706498.html?v1=185480924"
  },
  {
    "name": "PUFFER JACKET",
    "price": 199000,
    "discount": 71,
    "link": "https://www.zara.com/in/en/puffer-jacket-p06985333.html?v1=198084114"
  },
  {
    "name": "STRIPED JACKET",
    "price": 199000,
    "discount": 71,
    "link": "https://www.zara.com/in/en/striped-jacket-p03918315.html?v1=185138289"
  },
  {
    "name": "PUFFER JACKET",
    "price": 199000,
    "discount": 71,
    "link": "https://www.zara.com/in/en/puffer-jacket-p06985333.html?v1=205281130"
  },
  {
    "name": "PUFFER JACKET",
    "price": 199000,
    "discount": 71,
    "link": "https://www.zara.com/in/en/puffer-jacket-p06985333.html?v1=198084113"
  },
  {
    "name": "TEXTURED STRIPE JACKET",
    "price": 199000,
    "discount": 71,
    "link": "https://www.zara.com/in/en/textured-stripe-jacket-p00706310.html?v1=185138317"
  },
  {
    "name": "WELLIES",
    "price": 199000,
    "discount": 71,
    "link": "https://www.zara.com/in/en/wellies-p12020020.html?v1=190251340"
  },
  {
    "name": "WELLIES",
    "price": 199000,
    "discount": 71,
    "link": "https://www.zara.com/in/en/wellies-p12020020.html?v1=190251342"
  },
  {
    "name": "WELLIES",
    "price": 199000,
    "discount": 71,
    "link": "https://www.zara.com/in/en/wellies-p12020020.html?v1=190251341"
  },
  {
    "name": "STRIPED TEXTURED T-SHIRT",
    "price": 79000,
    "discount": 69,
    "link": "https://www.zara.com/in/en/striped-textured-t-shirt-p00977301.html?v1=177882649"
  },
  {
    "name": "FLOWING TOP",
    "price": 79000,
    "discount": 69,
    "link": "https://www.zara.com/in/en/flowing-top-p00722346.html?v1=195384344"
  },
  {
    "name": "TWILL OVERSHIRT SET STUDIO NICHOLSON",
    "price": 249000,
    "discount": 68,
    "link": "https://www.zara.com/in/en/twill-overshirt-set-studio-nicholson-p05960808.html?v1=197550396"
  },
  {
    "name": "QUILTED GILET JACKET",
    "price": 249000,
    "discount": 68,
    "link": "https://www.zara.com/in/en/quilted-gilet-jacket-p00706337.html?v1=205812814"
  },
  {
    "name": "SUIT TECHNICAL BLAZER",
    "price": 249000,
    "discount": 68,
    "link": "https://www.zara.com/in/en/suit-technical-blazer-p07380670.html?v1=185851249"
  },
  {
    "name": "CONTRAST CORDUROY JACKET",
    "price": 249000,
    "discount": 68,
    "link": "https://www.zara.com/in/en/contrast-corduroy-jacket-p00706339.html?v1=201662675"
  },
  {
    "name": "CHECK DOUBLE-FACED JACKET",
    "price": 249000,
    "discount": 68,
    "link": "https://www.zara.com/in/en/check-double-faced-jacket-p03918481.html?v1=203009876"
  },
  {
    "name": "COTTON PARKA",
    "price": 249000,
    "discount": 68,
    "link": "https://www.zara.com/in/en/cotton-parka-p06917423.html?v1=185876997"
  },
  {
    "name": "SHIRT WITH POCKET",
    "price": 129000,
    "discount": 67,
    "link": "https://www.zara.com/in/en/shirt-with-pocket-p06644455.html?v1=240787624"
  },
  {
    "name": "STRIPED SHIRT WITH POCKET",
    "price": 129000,
    "discount": 67,
    "link": "https://www.zara.com/in/en/striped-shirt-with-pocket-p05912765.html?v1=200752441"
  },
  {
    "name": "TURTLENECK SWEATER",
    "price": 129000,
    "discount": 67,
    "link": "https://www.zara.com/in/en/turtleneck-sweater-p00632305.html?v1=185463442"
  },
  {
    "name": "STRAIGHT FIT TROUSERS",
    "price": 129000,
    "discount": 67,
    "link": "https://www.zara.com/in/en/straight-fit-trousers-p05855662.html?v1=192076686"
  },
  {
    "name": "TEXTURED SWEATER WITH STRIPES",
    "price": 129000,
    "discount": 67,
    "link": "https://www.zara.com/in/en/textured-sweater-with-stripes-p06771315.html?v1=182865018"
  },
  {
    "name": "WIDE FIT TROUSERS",
    "price": 129000,
    "discount": 67,
    "link": "https://www.zara.com/in/en/wide-fit-trousers-p05991913.html?v1=200752522"
  },
  {
    "name": "CARROT-FIT TROUSERS",
    "price": 129000,
    "discount": 67,
    "link": "https://www.zara.com/in/en/carrot-fit-trousers-p05846662.html?v1=192076684"
  },
  {
    "name": "TEXTURED JOGGER WAIST TROUSERS",
    "price": 129000,
    "discount": 67,
    "link": "https://www.zara.com/in/en/textured-jogger-waist-trousers-p07147340.html?v1=196170671"
  },
  {
    "name": "FAUX LEATHER TROUSERS",
    "price": 129000,
    "discount": 67,
    "link": "https://www.zara.com/in/en/faux-leather-trousers-p05070462.html?v1=186006598"
  },
  {
    "name": "FAUX LEATHER TROUSERS",
    "price": 129000,
    "discount": 67,
    "link": "https://www.zara.com/in/en/faux-leather-trousers-p05070462.html?v1=186006596"
  },
  {
    "name": "FAUX LEATHER TROUSERS",
    "price": 129000,
    "discount": 67,
    "link": "https://www.zara.com/in/en/faux-leather-trousers-p05070462.html?v1=186006597"
  },
  {
    "name": "SWEATSHIRT WITH STRIPE AND ZIP",
    "price": 129000,
    "discount": 67,
    "link": "https://www.zara.com/in/en/sweatshirt-with-stripe-and-zip-p00761314.html?v1=191287017"
  },
  {
    "name": "LEATHER DRIVING LOAFERS",
    "price": 199000,
    "discount": 66,
    "link": "https://www.zara.com/in/en/leather-driving-loafers-p12660921.html?v1=177653495"
  },
  {
    "name": "NYLON BOOTS WITH LINING",
    "price": 199000,
    "discount": 66,
    "link": "https://www.zara.com/in/en/nylon-boots-with-lining-p12052820.html?v1=189347426"
  },
  {
    "name": "WATER-REPELLENT TECHNICAL JACKET",
    "price": 199000,
    "discount": 66,
    "link": "https://www.zara.com/in/en/water-repellent-technical-jacket-p03918109.html?v1=200060714"
  },
  {
    "name": "100% LINEN OVERSHIRT",
    "price": 249000,
    "discount": 64,
    "link": "https://www.zara.com/in/en/100-linen-overshirt-p00706384.html?v1=179143170"
  },
  {
    "name": "100% LINEN OVERSHIRT",
    "price": 249000,
    "discount": 64,
    "link": "https://www.zara.com/in/en/100-linen-overshirt-p00706384.html?v1=179143169"
  },
  {
    "name": "KNIT FABRIC RUNNING TRAINERS",
    "price": 229000,
    "discount": 61,
    "link": "https://www.zara.com/in/en/knit-fabric-running-trainers-p12308020.html?v1=177677942"
  },
  {
    "name": "MINIMALIST SNEAKERS",
    "price": 159000,
    "discount": 60,
    "link": "https://www.zara.com/in/en/minimalist-sneakers-p12232920.html?v1=177672632"
  },
  {
    "name": "TEXTURED TANK TOP",
    "price": 79000,
    "discount": 60,
    "link": "https://www.zara.com/in/en/textured-tank-top-p00977309.html?v1=185998419"
  },
  {
    "name": "LIGHTWEIGHT SHORT SLEEVE T-SHIRT",
    "price": 79000,
    "discount": 60,
    "link": "https://www.zara.com/in/en/lightweight-short-sleeve-t-shirt-p00722353.html?v1=191107553"
  },
  {
    "name": "CROPPED EXERCISE T-SHIRT",
    "price": 79000,
    "discount": 60,
    "link": "https://www.zara.com/in/en/cropped-exercise-t-shirt-p04335404.html?v1=203017386"
  },
  {
    "name": "LEATHER CLOGS",
    "price": 279000,
    "discount": 60,
    "link": "https://www.zara.com/in/en/leather-clogs-p12735020.html?v1=197040501"
  },
  {
    "name": "METALLIC SLOGAN T-SHIRT",
    "price": 79000,
    "discount": 60,
    "link": "https://www.zara.com/in/en/metallic-slogan-t-shirt-p04087315.html?v1=185472987"
  },
  {
    "name": "JAVIER S. MEDINA® LEATHER CLOGS",
    "price": 279000,
    "discount": 60,
    "link": "https://www.zara.com/in/en/javier-s--medina--leather-clogs-p12721020.html?v1=177653557"
  },
  {
    "name": "Leather cage sandals",
    "price": 279000,
    "discount": 60,
    "link": "https://www.zara.com/in/en/leather-cage-sandals-p12717020.html?v1=177666747"
  },
  {
    "name": "PHOTO PRINT T-SHIRT",
    "price": 79000,
    "discount": 60,
    "link": "https://www.zara.com/in/en/photo-print-t-shirt-p06224317.html?v1=186011220"
  },
  {
    "name": "OVERSIZE HEAVY WEIGHT T-SHIRT",
    "price": 79000,
    "discount": 58,
    "link": "https://www.zara.com/in/en/oversize-heavy-weight-t-shirt-p00526324.html?v1=192093726"
  },
  {
    "name": "PARKA WITH RUBBERISED FINISH",
    "price": 249000,
    "discount": 58,
    "link": "https://www.zara.com/in/en/parka-with-rubberised-finish-p08281412.html?v1=191124251"
  },
  {
    "name": "FAUX-PATENT CHUNKY SHOES",
    "price": 249000,
    "discount": 58,
    "link": "https://www.zara.com/in/en/faux-patent-chunky-shoes-p12409020.html?v1=196170732"
  },
  {
    "name": "TEXTURED OTTOMAN T-SHIRT",
    "price": 79000,
    "discount": 58,
    "link": "https://www.zara.com/in/en/textured-ottoman-t-shirt-p01887300.html?v1=177653421"
  },
  {
    "name": "COTTON BLAZER",
    "price": 249000,
    "discount": 58,
    "link": "https://www.zara.com/in/en/cotton-blazer-p04387300.html?v1=186820600"
  },
  {
    "name": "TECHNICAL WINDBREAKER PARKA",
    "price": 249000,
    "discount": 58,
    "link": "https://www.zara.com/in/en/technical-windbreaker-parka-p08574469.html?v1=186463132"
  },
  {
    "name": "TRETORN X ZARA WELLIES",
    "price": 599000,
    "discount": 57,
    "link": "https://www.zara.com/in/en/tretorn-x-zara-wellies-p12050020.html?v1=240772712"
  },
  {
    "name": "TRETORN X ZARA WELLIES",
    "price": 599000,
    "discount": 57,
    "link": "https://www.zara.com/in/en/tretorn-x-zara-wellies-p12050020.html?v1=240772713"
  },
  {
    "name": "CHECK SET SHIRT",
    "price": 129000,
    "discount": 56,
    "link": "https://www.zara.com/in/en/check-set-shirt-p00775321.html?v1=217147278"
  },
  {
    "name": "STRIPED SHIRT",
    "price": 129000,
    "discount": 56,
    "link": "https://www.zara.com/in/en/striped-shirt-p02688121.html?v1=208652926"
  },
  {
    "name": "OVERSIZED CORDUROY SHIRT",
    "price": 129000,
    "discount": 56,
    "link": "https://www.zara.com/in/en/oversized-corduroy-shirt-p00775313.html?v1=217147280"
  },
  {
    "name": "STRAIGHT FIT TROUSERS",
    "price": 129000,
    "discount": 56,
    "link": "https://www.zara.com/in/en/straight-fit-trousers-p06917370.html?v1=196153422"
  },
  {
    "name": "CARROT FIT TROUSERS",
    "price": 129000,
    "discount": 56,
    "link": "https://www.zara.com/in/en/carrot-fit-trousers-p05862330.html?v1=206271180"
  },
  {
    "name": "SLIM FIT CHINOS",
    "price": 129000,
    "discount": 56,
    "link": "https://www.zara.com/in/en/slim-fit-chinos-p06861233.html?v1=184088139"
  },
  {
    "name": "SLIM FIT CHINOS",
    "price": 129000,
    "discount": 56,
    "link": "https://www.zara.com/in/en/slim-fit-chinos-p06861233.html?v1=184088136"
  },
  {
    "name": "STRAIGHT FIT JEANS",
    "price": 129000,
    "discount": 56,
    "link": "https://www.zara.com/in/en/straight-fit-jeans-p08727410.html?v1=180465872"
  },
  {
    "name": "STRIPED SHIRT WITH POCKET",
    "price": 129000,
    "discount": 56,
    "link": "https://www.zara.com/in/en/striped-shirt-with-pocket-p05896263.html?v1=203471082"
  },
  {
    "name": "SLIM FIT CHINOS",
    "price": 129000,
    "discount": 56,
    "link": "https://www.zara.com/in/en/slim-fit-chinos-p06861233.html?v1=184088137"
  },
  {
    "name": "DENIM OVERSHIRT",
    "price": 129000,
    "discount": 56,
    "link": "https://www.zara.com/in/en/denim-overshirt-p06917335.html?v1=179127165"
  },
  {
    "name": "STRIPED SUIT TROUSERS",
    "price": 129000,
    "discount": 56,
    "link": "https://www.zara.com/in/en/striped-suit-trousers-p00775312.html?v1=189675765"
  },
  {
    "name": "FLAME PRINT SHIRT",
    "price": 129000,
    "discount": 56,
    "link": "https://www.zara.com/in/en/flame-print-shirt-p06085351.html?v1=203017352"
  },
  {
    "name": "OVERSIZED SHIRT",
    "price": 129000,
    "discount": 56,
    "link": "https://www.zara.com/in/en/oversized-shirt-p05570318.html?v1=189902561"
  },
  {
    "name": "TEXTURED SHIRT",
    "price": 129000,
    "discount": 56,
    "link": "https://www.zara.com/in/en/textured-shirt-p05588295.html?v1=191327422"
  },
  {
    "name": "TEXTURED SHIRT",
    "price": 129000,
    "discount": 56,
    "link": "https://www.zara.com/in/en/textured-shirt-p04688092.html?v1=202283028"
  },
  {
    "name": "STRIPED SHIRT",
    "price": 129000,
    "discount": 56,
    "link": "https://www.zara.com/in/en/striped-shirt-p05588634.html?v1=192642833"
  },
  {
    "name": "BASIC HIGH NECK SWEATER",
    "price": 129000,
    "discount": 56,
    "link": "https://www.zara.com/in/en/basic-high-neck-sweater-p00304302.html?v1=182641959"
  },
  {
    "name": "POPLIN SHIRT",
    "price": 129000,
    "discount": 56,
    "link": "https://www.zara.com/in/en/poplin-shirt-p02688101.html?v1=200060861"
  },
  {
    "name": "STRIPED SHIRT",
    "price": 129000,
    "discount": 56,
    "link": "https://www.zara.com/in/en/striped-shirt-p03717259.html?v1=197304204"
  },
  {
    "name": "STRIPED COTTON - LINEN SHIRT",
    "price": 129000,
    "discount": 56,
    "link": "https://www.zara.com/in/en/striped-cotton---linen-shirt-p02688230.html?v1=188540541"
  },
  {
    "name": "TIE-DYE PRINT SWEATSHIRT",
    "price": 129000,
    "discount": 56,
    "link": "https://www.zara.com/in/en/tie-dye-print-sweatshirt-p02795304.html?v1=184088117"
  },
  {
    "name": "TEXTURED SHIRT WITH POCKET",
    "price": 129000,
    "discount": 56,
    "link": "https://www.zara.com/in/en/textured-shirt-with-pocket-p07545360.html?v1=191801323"
  },
  {
    "name": "POPLIN SHIRT",
    "price": 129000,
    "discount": 56,
    "link": "https://www.zara.com/in/en/poplin-shirt-p02688101.html?v1=200060862"
  },
  {
    "name": "POPLIN SHIRT",
    "price": 129000,
    "discount": 56,
    "link": "https://www.zara.com/in/en/poplin-shirt-p01781584.html?v1=195934376"
  },
  {
    "name": "HIGH NECK SWEATSHIRT",
    "price": 129000,
    "discount": 56,
    "link": "https://www.zara.com/in/en/high-neck-sweatshirt-p04442353.html?v1=198084120"
  },
  {
    "name": "STRIPED SHIRT",
    "price": 129000,
    "discount": 56,
    "link": "https://www.zara.com/in/en/striped-shirt-p02688212.html?v1=191323562"
  },
  {
    "name": "OVERSIZE SWEATSHIRT WITH SLOGAN",
    "price": 129000,
    "discount": 56,
    "link": "https://www.zara.com/in/en/oversize-sweatshirt-with-slogan-p04087380.html?v1=205281105"
  },
  {
    "name": "POPLIN SHIRT",
    "price": 129000,
    "discount": 56,
    "link": "https://www.zara.com/in/en/poplin-shirt-p01781566.html?v1=195934372"
  },
  {
    "name": "HIGH NECK SWEATSHIRT",
    "price": 129000,
    "discount": 56,
    "link": "https://www.zara.com/in/en/high-neck-sweatshirt-p04442353.html?v1=198084117"
  },
  {
    "name": "PRINTED SWEATSHIRT WITH PATCH",
    "price": 129000,
    "discount": 56,
    "link": "https://www.zara.com/in/en/printed-sweatshirt-with-patch-p00962342.html?v1=202478345"
  },
  {
    "name": "POPLIN SHIRT",
    "price": 129000,
    "discount": 56,
    "link": "https://www.zara.com/in/en/poplin-shirt-p01781566.html?v1=195934371"
  },
  {
    "name": "KNIT JOGGERS",
    "price": 129000,
    "discount": 55,
    "link": "https://www.zara.com/in/en/knit-joggers-p05536302.html?v1=177648606"
  },
  {
    "name": "TEXTURED SWEATSHIRT",
    "price": 129000,
    "discount": 55,
    "link": "https://www.zara.com/in/en/textured-sweatshirt-p00526360.html?v1=197519679"
  },
  {
    "name": "EASY CARE TEXTURED SHIRT",
    "price": 129000,
    "discount": 55,
    "link": "https://www.zara.com/in/en/easy-care-textured-shirt-p03090404.html?v1=208299285"
  },
  {
    "name": "COMFORT JOGGER-WAIST TROUSERS",
    "price": 129000,
    "discount": 55,
    "link": "https://www.zara.com/in/en/comfort-jogger-waist-trousers-p06462315.html?v1=193523772"
  },
  {
    "name": "STUDDED SANDALS",
    "price": 229000,
    "discount": 54,
    "link": "https://www.zara.com/in/en/studded-sandals-p12782920.html?v1=180861249"
  },
  {
    "name": "CANVAS BOWLING BAG",
    "price": 499000,
    "discount": 54,
    "link": "https://www.zara.com/in/en/canvas-bowling-bag-p13115020.html?v1=200752470"
  },
  {
    "name": "COTTON T-SHIRT",
    "price": 79000,
    "discount": 50,
    "link": "https://www.zara.com/in/en/cotton-t-shirt-p06462300.html?v1=192668113"
  },
  {
    "name": "EASY CARE TEXTURED SHIRT",
    "price": 129000,
    "discount": 50,
    "link": "https://www.zara.com/in/en/easy-care-textured-shirt-p03090401.html?v1=185134387"
  },
  {
    "name": "BASIC JOGGING TROUSERS",
    "price": 129000,
    "discount": 50,
    "link": "https://www.zara.com/in/en/basic-jogging-trousers-p00761301.html?v1=201963828"
  },
  {
    "name": "EASY CARE TEXTURED SHIRT",
    "price": 129000,
    "discount": 50,
    "link": "https://www.zara.com/in/en/easy-care-textured-shirt-p03090401.html?v1=185134390"
  },
  {
    "name": "EASY CARE TEXTURED SHIRT",
    "price": 129000,
    "discount": 50,
    "link": "https://www.zara.com/in/en/easy-care-textured-shirt-p03090401.html?v1=185134389"
  },
  {
    "name": "ROUND NECK SWEATER",
    "price": 129000,
    "discount": 50,
    "link": "https://www.zara.com/in/en/round-neck-sweater-p02580304.html?v1=177662347"
  },
  {
    "name": "BASIC RIBBED T-SHIRT",
    "price": 79000,
    "discount": 50,
    "link": "https://www.zara.com/in/en/basic-ribbed-t-shirt-p00526314.html?v1=179366028"
  },
  {
    "name": "ROUND NECK SWEATER",
    "price": 129000,
    "discount": 50,
    "link": "https://www.zara.com/in/en/round-neck-sweater-p02580304.html?v1=177662345"
  },
  {
    "name": "DENIM SHIRT",
    "price": 129000,
    "discount": 50,
    "link": "https://www.zara.com/in/en/denim-shirt-p06987320.html?v1=177662254"
  },
  {
    "name": "EASY CARE TEXTURED SHIRT",
    "price": 129000,
    "discount": 50,
    "link": "https://www.zara.com/in/en/easy-care-textured-shirt-p03090409.html?v1=187682134"
  },
  {
    "name": "JAVIER S. MEDINA® LEATHER CROSSBODY BAG",
    "price": 499000,
    "discount": 50,
    "link": "https://www.zara.com/in/en/javier-s--medina--leather-crossbody-bag-p13509020.html?v1=179140676"
  },
  {
    "name": "CREASED-EFFECT BLAZER",
    "price": 249000,
    "discount": 50,
    "link": "https://www.zara.com/in/en/creased-effect-blazer-p07505301.html?v1=191124244"
  }
]
